{
  "contacts": [
    {
      "firstName": "Anton",
      "lastName": "Ber",
      "tel": "+380963854475",
      "id": 1
    },
    {
      "firstName": "Anton",
      "lastName": "Ber2",
      "tel": "+380963854475",
      "id": 2
    },
    {
      "firstName": "Anton",
      "lastName": "Ber3",
      "tel": "+380963854475",
      "id": 3
    },
    {
      "firstName": "Anton",
      "lastName": "Ber4",
      "tel": "+380963854475",
      "id": 4
    },
    {
      "firstName": "Anton",
      "lastName": "Ber5",
      "tel": "+380963854475",
      "id": 5
    },
    {
      "firstName": "Anton",
      "lastName": "Ber6",
      "tel": "+380963854475",
      "id": 6
    },
    {
      "firstName": "Anton",
      "lastName": "Ber7",
      "tel": "+380963854475",
      "id": 7
    }
  ]
}